{
    "name": "chords",
    "timeSignature": "4/4",
    "averageVelocity": 50,
	"copyright": "Copyright 2022 Jeffrey D. Mershon",
    "tracks": [
        {
            "name": "Beat of 8",
            "type": "beat",
            "period": 8,
            "endAt": 72
        },
        {
            "name": "Beat of 3",
            "type": "beat",
            "period": 3,
            "endAt": 72
        },
		{
            "name": "Beat of 2",
            "type": "beat",
            "period": 2,
            "endAt": 72
        },
		{
            "name": "Progression 1",
			"midiChannel": 0,
            "type": "progression",
            "keyOf": "C Natural Minor",
			"progressionCycles": ["3","7","5"],
			"progressionCycleMovement": ["-","+","-"],
			"progressionSource": 0,
			"progressionDirection": "-",
			"progressionCycleSource": 0,
			"progressionCycleDirection": "-",
			"includeInScore": true,
			"instrumentName": "Piano",
			"instrumentCode": 1,
			"beatUnit": 1,
			"tempo": 60
        }
    ]
}