{
    "name": "5_4_4_4-4",
    "timeSignature": "4/4",
    "averageVelocity": 50,
    "tracks": [
        {
            "name": "beat of 5",
            "type": "beat",
            "period": 5,
            "endAt": 25,
            "events": [
                {
                    "index": 0,
                    "duration": 5,
                    "count": 1
                },
                {
                    "index": 5,
                    "duration": 5,
                    "count": 1
                },
                {
                    "index": 10,
                    "duration": 5,
                    "count": 1
                },
                {
                    "index": 15,
                    "duration": 5,
                    "count": 1
                },
                {
                    "index": 20,
                    "duration": 5,
                    "count": 1
                }
            ],
            "run": false,
            "id": 0
        },
        {
            "name": "Fractional beat of 4",
            "type": "beat",
            "period": 4,
            "endAt": 20,
            "events": [
                {
                    "index": 0,
                    "duration": 4,
                    "count": 1
                },
                {
                    "index": 4,
                    "duration": 4,
                    "count": 1
                },
                {
                    "index": 8,
                    "duration": 4,
                    "count": 1
                },
                {
                    "index": 12,
                    "duration": 4,
                    "count": 1
                },
                {
                    "index": 16,
                    "duration": 4,
                    "count": 1
                }
            ],
            "run": false,
            "id": 1
        },
        {
            "name": "Fractional beat of 4",
            "type": "beat",
            "period": 4,
            "endAt": 20,
            "offsetFrom": 0,
            "offsetAmount": 1,
            "events": [
                {
                    "index": 5,
                    "duration": 4,
                    "count": 1
                },
                {
                    "index": 9,
                    "duration": 4,
                    "count": 1
                },
                {
                    "index": 13,
                    "duration": 4,
                    "count": 1
                },
                {
                    "index": 17,
                    "duration": 4,
                    "count": 1
                },
                {
                    "index": 21,
                    "duration": 4,
                    "count": 1
                }
            ],
            "run": false,
            "id": 2
        },
        {
            "name": "beat of 5",
            "type": "beat",
            "period": 5,
            "endAt": 20,
            "events": [
                {
                    "index": 0,
                    "duration": 5,
                    "count": 1
                },
                {
                    "index": 5,
                    "duration": 5,
                    "count": 1
                },
                {
                    "index": 10,
                    "duration": 5,
                    "count": 1
                },
                {
                    "index": 15,
                    "duration": 5,
                    "count": 1
                }
            ],
            "run": false,
            "id": 3
        },
        {
            "name": "beat of 4",
            "type": "beat",
            "period": 4,
            "endAt": 20,
            "events": [
                {
                    "index": 0,
                    "duration": 4,
                    "count": 1
                },
                {
                    "index": 4,
                    "duration": 4,
                    "count": 1
                },
                {
                    "index": 8,
                    "duration": 4,
                    "count": 1
                },
                {
                    "index": 12,
                    "duration": 4,
                    "count": 1
                },
                {
                    "index": 16,
                    "duration": 4,
                    "count": 1
                }
            ],
            "run": false,
            "id": 4
        },
        {
            "name": "Fractional interference rhythm combining 5 and 4",
            "type": "rhythm",
            "sources": [
                {
                    "source": 0
                },
                {
                    "source": 1
                },
                {
                    "source": 2
                }
            ],
            "includeInScore": false,
            "tempo": 80,
            "events": [
                {
                    "index": 0,
                    "duration": 4,
                    "count": 2
                },
                {
                    "index": 4,
                    "duration": 1,
                    "count": 1
                },
                {
                    "index": 5,
                    "duration": 3,
                    "count": 2
                },
                {
                    "index": 8,
                    "duration": 1,
                    "count": 1
                },
                {
                    "index": 9,
                    "duration": 1,
                    "count": 1
                },
                {
                    "index": 10,
                    "duration": 2,
                    "count": 1
                },
                {
                    "index": 12,
                    "duration": 1,
                    "count": 1
                },
                {
                    "index": 13,
                    "duration": 2,
                    "count": 1
                },
                {
                    "index": 15,
                    "duration": 1,
                    "count": 1
                },
                {
                    "index": 16,
                    "duration": 1,
                    "count": 1
                },
                {
                    "index": 17,
                    "duration": 3,
                    "count": 1
                },
                {
                    "index": 20,
                    "duration": 1,
                    "count": 1
                },
                {
                    "index": 21,
                    "duration": 4,
                    "count": 1
                }
            ],
            "run": false,
            "id": 5,
            "endAt": 21,
            "LCM": 20
        },
        {
            "name": "Interference rhythm combining 5 and 4",
            "type": "rhythm",
            "sources": [
                {
                    "source": 3
                },
                {
                    "source": 4
                }
            ],
            "includeInScore": false,
            "computeLCM": true,
            "beatUnit": 4,
            "defaultPitch": "C4",
            "tempo": 90,
            "events": [
                {
                    "index": 0,
                    "duration": 4,
                    "count": 2
                },
                {
                    "index": 4,
                    "duration": 1,
                    "count": 1
                },
                {
                    "index": 5,
                    "duration": 3,
                    "count": 1
                },
                {
                    "index": 8,
                    "duration": 2,
                    "count": 1
                },
                {
                    "index": 10,
                    "duration": 2,
                    "count": 1
                },
                {
                    "index": 12,
                    "duration": 3,
                    "count": 1
                },
                {
                    "index": 15,
                    "duration": 1,
                    "count": 1
                },
                {
                    "index": 16,
                    "duration": 4,
                    "count": 1
                }
            ],
            "run": false,
            "id": 6,
            "endAt": 16,
            "LCM": 20
        },
        {
            "name": "Interference rhythm appending tracks 5 and 6",
            "type": "concatenate",
            "sources": [
                {
                    "source": 5
                },
                {
                    "source": 6
                }
            ],
            "includeInScore": true,
            "computeLCM": true,
            "beatUnit": 4,
            "defaultPitch": "C4",
            "tempo": 90,
            "events": [
                {
                    "index": 0,
                    "duration": 4,
                    "count": 2
                },
                {
                    "index": 4,
                    "duration": 1,
                    "count": 1
                },
                {
                    "index": 5,
                    "duration": 3,
                    "count": 2
                },
                {
                    "index": 8,
                    "duration": 1,
                    "count": 1
                },
                {
                    "index": 9,
                    "duration": 1,
                    "count": 1
                },
                {
                    "index": 10,
                    "duration": 2,
                    "count": 1
                },
                {
                    "index": 12,
                    "duration": 1,
                    "count": 1
                },
                {
                    "index": 13,
                    "duration": 2,
                    "count": 1
                },
                {
                    "index": 15,
                    "duration": 1,
                    "count": 1
                },
                {
                    "index": 16,
                    "duration": 1,
                    "count": 1
                },
                {
                    "index": 17,
                    "duration": 3,
                    "count": 1
                },
                {
                    "index": 20,
                    "duration": 1,
                    "count": 1
                },
                {
                    "index": 21,
                    "duration": 4,
                    "count": 1
                },
                {
                    "index": 25,
                    "duration": 4,
                    "count": 2
                },
                {
                    "index": 29,
                    "duration": 1,
                    "count": 1
                },
                {
                    "index": 30,
                    "duration": 3,
                    "count": 1
                },
                {
                    "index": 33,
                    "duration": 2,
                    "count": 1
                },
                {
                    "index": 35,
                    "duration": 2,
                    "count": 1
                },
                {
                    "index": 37,
                    "duration": 3,
                    "count": 1
                },
                {
                    "index": 40,
                    "duration": 1,
                    "count": 1
                },
                {
                    "index": 41,
                    "duration": 4,
                    "count": 1
                }
            ],
            "run": false,
            "id": 7,
            "LCM": 20
        }
    ],
    "defaultPitch": "C4",
    "tempo": 90
}