{
    "name": "3_2_8_6-8",
    "timeSignature": "6/8",
    "averageVelocity": 50,
    "tracks": [
        {
            "name": "beat of 3",
            "type": "beat",
            "period": 3,
            "endAt": 9,
            "events": [
                {
                    "index": 0,
                    "duration": 3,
                    "count": 1
                },
                {
                    "index": 3,
                    "duration": 3,
                    "count": 1
                },
                {
                    "index": 6,
                    "duration": 3,
                    "count": 1
                }
            ],
            "run": false,
            "id": 0
        },
        {
            "name": "Fractional beat of 2",
            "type": "beat",
            "period": 2,
            "endAt": 6,
            "events": [
                {
                    "index": 0,
                    "duration": 2,
                    "count": 1
                },
                {
                    "index": 2,
                    "duration": 2,
                    "count": 1
                },
                {
                    "index": 4,
                    "duration": 2,
                    "count": 1
                }
            ],
            "run": false,
            "id": 1
        },
        {
            "name": "Fractional beat of 2",
            "type": "beat",
            "period": 2,
            "endAt": 6,
            "offsetFrom": 0,
            "offsetAmount": 1,
            "events": [
                {
                    "index": 3,
                    "duration": 2,
                    "count": 1
                },
                {
                    "index": 5,
                    "duration": 2,
                    "count": 1
                },
                {
                    "index": 7,
                    "duration": 2,
                    "count": 1
                }
            ],
            "run": false,
            "id": 2
        },
        {
            "name": "beat of 3",
            "type": "beat",
            "period": 3,
            "endAt": 6,
            "events": [
                {
                    "index": 0,
                    "duration": 3,
                    "count": 1
                },
                {
                    "index": 3,
                    "duration": 3,
                    "count": 1
                }
            ],
            "run": false,
            "id": 3
        },
        {
            "name": "beat of 2",
            "type": "beat",
            "period": 2,
            "endAt": 6,
            "events": [
                {
                    "index": 0,
                    "duration": 2,
                    "count": 1
                },
                {
                    "index": 2,
                    "duration": 2,
                    "count": 1
                },
                {
                    "index": 4,
                    "duration": 2,
                    "count": 1
                }
            ],
            "run": false,
            "id": 4
        },
        {
            "name": "Fractional interference rhythm combining 3 and 2",
            "type": "rhythm",
            "sources": [
                {
                    "source": 0
                },
                {
                    "source": 1
                },
                {
                    "source": 2
                }
            ],
            "includeInScore": false,
            "tempo": 80,
            "events": [
                {
                    "index": 0,
                    "duration": 2,
                    "count": 2
                },
                {
                    "index": 2,
                    "duration": 1,
                    "count": 1
                },
                {
                    "index": 3,
                    "duration": 1,
                    "count": 2
                },
                {
                    "index": 4,
                    "duration": 1,
                    "count": 1
                },
                {
                    "index": 5,
                    "duration": 1,
                    "count": 1
                },
                {
                    "index": 6,
                    "duration": 1,
                    "count": 1
                },
                {
                    "index": 7,
                    "duration": 2,
                    "count": 1
                }
            ],
            "run": false,
            "id": 5,
            "endAt": 7,
            "LCM": 6
        },
        {
            "name": "Interference rhythm combining 3 and 2",
            "type": "rhythm",
            "sources": [
                {
                    "source": 3
                },
                {
                    "source": 4
                }
            ],
            "includeInScore": false,
            "computeLCM": true,
            "beatUnit": 8,
            "defaultPitch": "C4",
            "tempo": 90,
            "events": [
                {
                    "index": 0,
                    "duration": 2,
                    "count": 2
                },
                {
                    "index": 2,
                    "duration": 1,
                    "count": 1
                },
                {
                    "index": 3,
                    "duration": 1,
                    "count": 1
                },
                {
                    "index": 4,
                    "duration": 2,
                    "count": 1
                }
            ],
            "run": false,
            "id": 6,
            "endAt": 4,
            "LCM": 6
        },
        {
            "name": "Interference rhythm appending tracks 5 and 6",
            "type": "concatenate",
            "sources": [
                {
                    "source": 6
                },
                {
                    "source": 5
                }
            ],
            "includeInScore": true,
            "computeLCM": true,
            "beatUnit": 8,
            "defaultPitch": "C4",
            "tempo": 90,
            "events": [
                {
                    "index": 0,
                    "duration": 2,
                    "count": 2
                },
                {
                    "index": 2,
                    "duration": 1,
                    "count": 1
                },
                {
                    "index": 3,
                    "duration": 1,
                    "count": 1
                },
                {
                    "index": 4,
                    "duration": 2,
                    "count": 1
                },
                {
                    "index": 6,
                    "duration": 2,
                    "count": 2
                },
                {
                    "index": 8,
                    "duration": 1,
                    "count": 1
                },
                {
                    "index": 9,
                    "duration": 1,
                    "count": 2
                },
                {
                    "index": 10,
                    "duration": 1,
                    "count": 1
                },
                {
                    "index": 11,
                    "duration": 1,
                    "count": 1
                },
                {
                    "index": 12,
                    "duration": 1,
                    "count": 1
                },
                {
                    "index": 13,
                    "duration": 2,
                    "count": 1
                }
            ],
            "run": false,
            "id": 7,
            "LCM": 6
        }
    ],
    "defaultPitch": "C4",
    "tempo": 90
}